Metadata-Version: 2.1
Name: secure-delete
Version: 0.0.2
Summary: A tool for safely delete files.
Home-page: https://github.com/wevsty/secure_delete
Author: wevsty
Author-email: ty@wevs.org
License: UNKNOWN
Platform: UNKNOWN
Classifier: License :: OSI Approved :: MIT License
Classifier: Programming Language :: Python :: 3
Classifier: Programming Language :: Python :: Implementation :: CPython
